CHANGELOG.md
LICENSE
README.md
meilisync/__init__.py
meilisync/discover.py
meilisync/enums.py
meilisync/event.py
meilisync/main.py
meilisync/meili.py
meilisync/plugin.py
meilisync/progress/__init__.py
meilisync/progress/file.py
meilisync/progress/redis.py
meilisync/schemas.py
meilisync/settings.py
meilisync/source/__init__.py
meilisync/source/mongo.py
meilisync/source/mysql.py
meilisync/source/postgres.py
meilisync/version.py
meilisync-0.1.3.dist-info/LICENSE
meilisync-0.1.3.dist-info/METADATA
meilisync-0.1.3.dist-info/WHEEL
meilisync-0.1.3.dist-info/entry_points.txt
meilisync-0.1.3.dist-info/RECORD
