Metadata-Version: 2.1
Name: meilisync
Version: 0.1.3
Summary: Realtime sync data from MySQL/PostgreSQL/MongoDB to meilisearch
Home-page: https://github.com/long2ice/meilisync.git
License: Apache-2.0
Keywords: meilisearch,postgres,mysql,mongodb,sync
Author: long2ice
Author-email: long2ice@gmail.com
Requires-Python: >=3.9,<4.0
Classifier: License :: OSI Approved :: Apache Software License
Classifier: Programming Language :: Python :: 3
Classifier: Programming Language :: Python :: 3.9
Classifier: Programming Language :: Python :: 3.10
Classifier: Programming Language :: Python :: 3.11
Classifier: Programming Language :: Python :: 3.12
Provides-Extra: all
Provides-Extra: mongodb
Provides-Extra: mysql
Provides-Extra: postgres
Provides-Extra: redis
Provides-Extra: sentry
Requires-Dist: aiofiles
Requires-Dist: asyncmy (>=0.2.9,<0.3.0) ; extra == "all" or extra == "mysql"
Requires-Dist: loguru
Requires-Dist: meilisearch-python-sdk
Requires-Dist: motor ; extra == "all" or extra == "mongodb"
Requires-Dist: psycopg2-binary ; extra == "all" or extra == "postgres"
Requires-Dist: pydantic-settings
Requires-Dist: pyyaml
Requires-Dist: redis ; extra == "all" or extra == "redis"
Requires-Dist: sentry-sdk ; extra == "all" or extra == "sentry"
Requires-Dist: typer[all]
Project-URL: Documentation, https://github.com/meilisync/meilisync
Project-URL: Repository, https://github.com/long2ice/meilisync.git
